Mycolormap.py
mycolormap-1.0.dist-info/METADATA
mycolormap-1.0.dist-info/WHEEL
mycolormap-1.0.dist-info/top_level.txt
mycolormap-1.0.dist-info/RECORD
