Metadata-Version: 2.1
Name: mycolormap
Version: 1.0
Summary: 为降水图片制作色表用
Home-page: UNKNOWN
Author: Wang Zhao Qiang
Author-email: 349558455@qq.com
License: UNKNOWN
Platform: UNKNOWN
